semterm/__init__.py
semterm/main.py
semterm/UI/UserInterface.py
semterm/UI/__init__.py
semterm/agent/SemanticTerminalAgent.py
semterm/agent/TerminalAgent.py
semterm/agent/TerminalAgentPrompt.py
semterm/agent/__init__.py
semterm/config/Config.py
semterm/config/__init__.py
semterm/config/config.ini
semterm/langchain_extensions/__init__.py
semterm/langchain_extensions/schema.py
semterm/langchain_extensions/tools.py
semterm/terminal/SemanticTerminalManager.py
semterm/terminal/SemanticTerminalProcess.py
semterm/terminal/TerminalOutputParser.py
semterm/terminal/TerminalTool.py
semterm/terminal/__init__.py
tests/__init__.py
tests/conftest.py
tests/test_main.py
tests/UI/__init__.py
tests/UI/test_UserInterface.py
tests/agent/__init__.py
tests/agent/test_SemanticTerminalAgent.py
tests/agent/test_TerminalAgent.py
tests/agent/test_TerminalAgentPrompt.py
tests/terminal/__init__.py
tests/terminal/test_SemanticTerminalManager.py
tests/terminal/test_SemanticTerminalProcess.py
tests/terminal/test_TerminalOutputParser.py
tests/terminal/test_TerminalTool.py
tests/tools/__init__.py
tests/tools/test_tools.py
semterm-0.6.1.dist-info/LICENSE
semterm-0.6.1.dist-info/METADATA
semterm-0.6.1.dist-info/WHEEL
semterm-0.6.1.dist-info/entry_points.txt
semterm-0.6.1.dist-info/top_level.txt
semterm-0.6.1.dist-info/RECORD
