Metadata-Version: 2.1
Name: semterm
Version: 0.6.1
Summary: The Semantic Terminal
Author: Lambrou
Author-email: alexanderlambrou0602@gmail.com
License-File: LICENSE
Requires-Dist: langchain
Requires-Dist: langchain-community
Requires-Dist: langchain-experimental
Requires-Dist: langchain-openai
Requires-Dist: pexpect
Requires-Dist: pydantic
